mkdocs_git_revision_date_localized_plugin/__init__.py
mkdocs_git_revision_date_localized_plugin/ci.py
mkdocs_git_revision_date_localized_plugin/dates.py
mkdocs_git_revision_date_localized_plugin/exclude.py
mkdocs_git_revision_date_localized_plugin/plugin.py
mkdocs_git_revision_date_localized_plugin/util.py
mkdocs_git_revision_date_localized_plugin/css/timeago.css
mkdocs_git_revision_date_localized_plugin/js/timeago.min.js
mkdocs_git_revision_date_localized_plugin/js/timeago_mkdocs_material.js
mkdocs_git_revision_date_localized_plugin-1.4.4.dist-info/LICENSE
mkdocs_git_revision_date_localized_plugin-1.4.4.dist-info/METADATA
mkdocs_git_revision_date_localized_plugin-1.4.4.dist-info/WHEEL
mkdocs_git_revision_date_localized_plugin-1.4.4.dist-info/entry_points.txt
mkdocs_git_revision_date_localized_plugin-1.4.4.dist-info/top_level.txt
mkdocs_git_revision_date_localized_plugin-1.4.4.dist-info/RECORD
