Metadata-Version: 2.2
Name: mkdocs-git-revision-date-localized-plugin
Version: 1.4.4
Summary: Mkdocs plugin that enables displaying the localized date of the last git modification of a markdown file.
Author-email: Tim Vink <vinktim@gmail.com>
License: MIT
Project-URL: Homepage, https://github.com/timvink/mkdocs-git-revision-date-localized-plugin
Keywords: mkdocs,plugin
Classifier: Operating System :: OS Independent
Classifier: Programming Language :: Python
Classifier: Programming Language :: Python :: 3
Classifier: Programming Language :: Python :: 3.8
Classifier: Programming Language :: Python :: 3.9
Classifier: Programming Language :: Python :: 3.10
Classifier: Programming Language :: Python :: 3.11
Classifier: Programming Language :: Python :: 3.12
Classifier: Programming Language :: Python :: 3.13
Classifier: License :: OSI Approved :: MIT License
Requires-Python: >=3.8
License-File: LICENSE
Requires-Dist: babel>=2.7.0
Requires-Dist: gitpython>=3.1.44
Requires-Dist: mkdocs>=1.0
Requires-Dist: pytz>=2025.1
